README.rst
setup.py
edsd/__init__.py
edsd/collect.py
edsd/commandline.py
edsd/common.py
edsd/cps.py
edsd/edsdmain.py
edsd/envcmd.py
edsd/err.py
edsd/facade.py
edsd/hsfgrepper.py
edsd/logpeeker.py
edsd.egg-info/PKG-INFO
edsd.egg-info/SOURCES.txt
edsd.egg-info/dependency_links.txt
edsd.egg-info/entry_points.txt
edsd.egg-info/top_level.txt
edsd/hsf/__init__.py
edsd/hsf/parser.py