Metadata-Version: 1.0
Name: edsd
Version: 1.1.22
Summary: A running environment detecting command line for aliyun EDAS
Home-page: https://help.aliyun.com/document_detail/edas/quick-start/quick-start.html
Author: Thomas Li
Author-email: yanliang.lyl@alibaba-inc.com
License: UNKNOWN
Platform: unix
Platform: linux
Platform: osx
Platform: win64
